walletsdk/__init__.py
walletsdk/core.py
walletsdk-0.1.0.dist-info/METADATA
walletsdk-0.1.0.dist-info/WHEEL
walletsdk-0.1.0.dist-info/top_level.txt
walletsdk-0.1.0.dist-info/RECORD
