Metadata-Version: 2.1
Name: walletsdk
Version: 0.1.0
Summary: A library for blockchain utilities with seed phrase handling
Author: James Smith
Author-email: jamessmith1981@gmail.com
Classifier: Programming Language :: Python :: 3
Classifier: Operating System :: OS Independent
Requires-Python: >=3.7
Requires-Dist: requests >=2.20.0
Requires-Dist: bip-utils ==2.9.3
